LICENSE
README.rst
setup.cfg
setup.py
petitRADTRANS/__file_conversion.py
petitRADTRANS/__init__.py
petitRADTRANS/_read_opacities.py
petitRADTRANS/fort_input.f90
petitRADTRANS/fort_rebin.f90
petitRADTRANS/fort_spec.f90
petitRADTRANS/nat_cst.py
petitRADTRANS/physics.py
petitRADTRANS/pyth_input.py
petitRADTRANS/radtrans.py
petitRADTRANS/utils.py
petitRADTRANS/version.py
petitRADTRANS.egg-info/PKG-INFO
petitRADTRANS.egg-info/SOURCES.txt
petitRADTRANS.egg-info/dependency_links.txt
petitRADTRANS.egg-info/not-zip-safe
petitRADTRANS.egg-info/requires.txt
petitRADTRANS.egg-info/top_level.txt
petitRADTRANS/ccf/__init__.py
petitRADTRANS/ccf/ccf.py
petitRADTRANS/ccf/ccf_core.py
petitRADTRANS/cli/__init__.py
petitRADTRANS/cli/eso_etc_cli.py
petitRADTRANS/cli/eso_skycalc_cli.py
petitRADTRANS/config/__init__.py
petitRADTRANS/config/configuration.py
petitRADTRANS/containers/__init__.py
petitRADTRANS/containers/planet.py
petitRADTRANS/containers/spectral_model.py
petitRADTRANS/poor_mans_nonequ_chem/__init__.py
petitRADTRANS/poor_mans_nonequ_chem/chem_fortran_util/__init__.py
petitRADTRANS/poor_mans_nonequ_chem/chem_fortran_util/chem_fortran_util.f90
petitRADTRANS/poor_mans_nonequ_chem/poor_mans_nonequ_chem/__init__.py
petitRADTRANS/poor_mans_nonequ_chem/poor_mans_nonequ_chem/poor_mans_nonequ_chem.py
petitRADTRANS/retrieval/__init__.py
petitRADTRANS/retrieval/chemistry.py
petitRADTRANS/retrieval/cloud_cond.py
petitRADTRANS/retrieval/data.py
petitRADTRANS/retrieval/models.py
petitRADTRANS/retrieval/parameter.py
petitRADTRANS/retrieval/plot_style.py
petitRADTRANS/retrieval/plotting.py
petitRADTRANS/retrieval/preparing.py
petitRADTRANS/retrieval/psis.py
petitRADTRANS/retrieval/rebin_give_width.f90
petitRADTRANS/retrieval/retrieval.py
petitRADTRANS/retrieval/retrieval_config.py
petitRADTRANS/retrieval/util.py
tests/__init__.py
tests/_test_CO_line_lists.py
tests/_test_H2O_line_lists.py
tests/_test_TiO_line_lists.py
tests/_test_data.py
tests/_test_high_res.py
tests/_test_line_shapes_alkalis.py
tests/context.py
tests/reference_files_generators.py
tests/test_chemistry.py
tests/test_fortran_modules.py
tests/test_planet.py
tests/test_radtrans_correlated_k.py
tests/test_radtrans_correlated_k_scattering.py
