Metadata-Version: 2.1
Name: petitRADTRANS
Version: 2.7.6
Summary: Exoplanet spectral synthesis tool for retrievals
Home-page: https://gitlab.com/mauricemolli/petitRADTRANS
Author: Paul Mollière
Author-email: molliere@mpia.de
License: MIT License
License-File: LICENSE
